block_spinning
