Metadata-Version: 1.1
Name: block-spinning
Version: 1.0.1
Summary: A Python module for block spinning
Home-page: http://github.com/KeizerDev/block_spinning
Author: KeizerDev
Author-email: UNKNOWN
License: GPLv3
Download-URL: https://github.com/KeizerDev/block_spinning/archive/master.zip
Keywords: block spin,block spin,block spinning,spinning,text spin
Platform: UNKNOWN
Classifier: Programming Language :: Python
Classifier: Programming Language :: Python :: 2
Classifier: Programming Language :: Python :: 3
Classifier: Operating System :: OS Independent
Classifier: Topic :: Text Processing
Classifier: License :: OSI Approved :: GNU General Public License v3 (GPLv3)
